fasttext_serving/__init__.py
fasttext_serving/predict_pb2.py
fasttext_serving/predict_pb2_grpc.py
fasttext_serving-0.2.0.dist-info/METADATA
fasttext_serving-0.2.0.dist-info/WHEEL
fasttext_serving-0.2.0.dist-info/top_level.txt
fasttext_serving-0.2.0.dist-info/RECORD
